pyspark_ds_toolbox/__init__.py
pyspark_ds_toolbox/causal_inference/__init__.py
pyspark_ds_toolbox/causal_inference/diff_in_diff.py
pyspark_ds_toolbox/causal_inference/ps_matching.py
pyspark_ds_toolbox/ml/__init__.py
pyspark_ds_toolbox/ml/classification/__init__.py
pyspark_ds_toolbox/ml/classification/baseline_classifiers.py
pyspark_ds_toolbox/ml/classification/eval.py
pyspark_ds_toolbox/ml/data_prep/__init__.py
pyspark_ds_toolbox/ml/data_prep/class_weights.py
pyspark_ds_toolbox/ml/data_prep/features_vector.py
pyspark_ds_toolbox/ml/feature_importance/__init__.py
pyspark_ds_toolbox/ml/feature_importance/native_spark.py
pyspark_ds_toolbox/ml/feature_importance/shap_values.py
pyspark_ds_toolbox/ml/feature_selection/__init__.py
pyspark_ds_toolbox/ml/feature_selection/information_value.py
pyspark_ds_toolbox/stats/__init__.py
pyspark_ds_toolbox/stats/association.py
pyspark_ds_toolbox/wrangling/__init__.py
pyspark_ds_toolbox/wrangling/data_quality.py
pyspark_ds_toolbox/wrangling/reshape.py
pyspark_ds_toolbox-0.4.3.dist-info/LICENSE.md
pyspark_ds_toolbox-0.4.3.dist-info/WHEEL
pyspark_ds_toolbox-0.4.3.dist-info/METADATA
pyspark_ds_toolbox-0.4.3.dist-info/RECORD
