Metadata-Version: 2.1
Name: pyspark-ds-toolbox
Version: 0.4.3
Summary: A Pyspark companion for data science tasks.
Home-page: https://github.com/viniciusmsousa/pyspark-ds-toolbox
License: GPL-3.0-only
Author: vinicius.sousa
Author-email: vinisousa04@gmail.com
Requires-Python: >=3.7.1,<3.10
Classifier: License :: OSI Approved :: GNU General Public License v3 (GPLv3)
Classifier: Programming Language :: Python :: 3
Classifier: Programming Language :: Python :: 3.8
Classifier: Programming Language :: Python :: 3.9
Requires-Dist: h2o (>=3.34.0,<4.0.0)
Requires-Dist: matplotlib (>=3.5.1,<4.0.0)
Requires-Dist: mlflow (>=1.22.0,<2.0.0)
Requires-Dist: numpy (==1.21.0)
Requires-Dist: pandas (>=1.3.4,<2.0.0)
Requires-Dist: pyarrow (>=6.0.1,<7.0.0)
Requires-Dist: pyspark (>=3.2)
Requires-Dist: seaborn (>=0.11.2,<0.12.0)
Requires-Dist: tqdm (>=4.62.3,<5.0.0)
Requires-Dist: typeguard (>=2.13.2,<3.0.0)
Project-URL: Documentation, https://viniciusmsousa.github.io/pyspark-ds-toolbox/index.html
Project-URL: Repository, https://github.com/viniciusmsousa/pyspark-ds-toolbox
